aqstat/__init__.py
aqstat/aqdata.py
aqstat/cli/__init__.py
aqstat/cli/__main__.py
aqstat/cli/commands/download.py
aqstat/cli/commands/plot.py
aqstat/cli/commands/stat.py
aqstat/cli/commands/test.py
aqstat/cli/main.py
aqstat/locales/aqstat.pot
aqstat/locales/hu/LC_MESSAGES/aqstat.mo
aqstat/locales/hu/LC_MESSAGES/aqstat.po
aqstat/locales/README.md
aqstat/metadata.py
aqstat/parse.py
aqstat/plot.py
aqstat/scripts/convert_google_form_csv_to_metadata_json.py
aqstat/scripts/convert_luftdaten_csv_to_metadata_json.py
aqstat/stat.py
aqstat/utils.py
aqstat-1.0.1.dist-info/entry_points.txt
aqstat-1.0.1.dist-info/LICENSE.md
aqstat-1.0.1.dist-info/WHEEL
aqstat-1.0.1.dist-info/METADATA
aqstat-1.0.1.dist-info/RECORD
