Metadata-Version: 2.1
Name: aqstat
Version: 1.0.1
Summary: Toolset for visualizing Air Quality Data from https://sensor.community
Home-page: https://github.com/vasarhelyi/aqstat
License: MIT
Keywords: air quality,air pollution,sensor.community,luftdaten.info
Author: Gabor Vasarhelyi
Author-email: vasarhelyi@hal.elte.hu
Requires-Python: >=3.7.1,<4.0.0
Classifier: License :: OSI Approved :: MIT License
Classifier: Programming Language :: Python :: 3
Classifier: Programming Language :: Python :: 3.8
Classifier: Programming Language :: Python :: 3.9
Requires-Dist: asks (>=2.4.12,<3.0.0)
Requires-Dist: click (>=7.1.2,<8.0.0)
Requires-Dist: click-option-group (>=0.5.2,<0.6.0)
Requires-Dist: matplotlib (>=3.3.4,<4.0.0)
Requires-Dist: pandas (>=1.2.3,<2.0.0)
Requires-Dist: requests (>=2.25.1,<3.0.0)
Requires-Dist: trio (>=0.18.0,<0.19.0)
Project-URL: Repository, https://github.com/vasarhelyi/aqstat
